ask_me/__init__.py
ask_me/config.py
ask_me/extensions.py
ask_me/wrapper.py
ask_me/blueprint/__init__.py
ask_me/blueprint/auth_blueprint.py
ask_me/blueprint/question_blueprint.py
ask_me/dist/favicon.png
ask_me/dist/index.html
ask_me/dist/static/FiraCode-Regular-CRwVj4V2.woff2
ask_me/dist/static/LatoLatin-Regular-Dmlz1U0B.woff2
ask_me/dist/static/LatoLatin-Semibold-Dbk81p2D.woff2
ask_me/dist/static/index-BuUDkVbs.css
ask_me/dist/static/index-DZ8E1NBq.css
ask_me/dist/static/index-Hw7v7zZk.js
ask_me/dist/static/index-x8-1h3AX.js
ask_me/dist/static/css/app.0806d729.css
ask_me/dist/static/css/app.26cc3d14.css
ask_me/dist/static/css/app.2cd70fbd.css
ask_me/dist/static/css/app.31b9b6b1.css
ask_me/dist/static/css/app.3ca6e424.css
ask_me/dist/static/css/app.4cc0a198.css
ask_me/dist/static/css/app.53345f55.css
ask_me/dist/static/css/app.666d5d89.css
ask_me/dist/static/css/app.8e3fa91d.css
ask_me/dist/static/css/app.f5a82e8b.css
ask_me/dist/static/css/chunk-vendors.16614ec7.css
ask_me/dist/static/fonts/FiraCode-Regular.ea8e3416.woff2
ask_me/dist/static/fonts/LatoLatin-Regular.3cd36578.woff2
ask_me/dist/static/fonts/LatoLatin-Semibold.008763cc.woff2
ask_me/dist/static/js/app.1af6faf0.js
ask_me/dist/static/js/app.1af6faf0.js.map
ask_me/dist/static/js/app.2402be66.js
ask_me/dist/static/js/app.2402be66.js.map
ask_me/dist/static/js/app.2bd111e2.js
ask_me/dist/static/js/app.2bd111e2.js.map
ask_me/dist/static/js/app.3213aa6a.js
ask_me/dist/static/js/app.3213aa6a.js.map
ask_me/dist/static/js/app.5d5f6fdf.js
ask_me/dist/static/js/app.5d5f6fdf.js.map
ask_me/dist/static/js/app.60b323b0.js
ask_me/dist/static/js/app.60b323b0.js.map
ask_me/dist/static/js/app.71291211.js
ask_me/dist/static/js/app.71291211.js.map
ask_me/dist/static/js/app.80dc9a6d.js
ask_me/dist/static/js/app.80dc9a6d.js.map
ask_me/dist/static/js/app.8b5d91d1.js
ask_me/dist/static/js/app.8b5d91d1.js.map
ask_me/dist/static/js/app.9a4eb7ed.js
ask_me/dist/static/js/app.9a4eb7ed.js.map
ask_me/dist/static/js/app.aa71b4fe.js
ant_ask_me-1.2.0.dist-info/LICENSE
ant_ask_me-1.2.0.dist-info/METADATA
ant_ask_me-1.2.0.dist-info/WHEEL
ant_ask_me-1.2.0.dist-info/top_level.txt
ant_ask_me-1.2.0.dist-info/RECORD
