Metadata-Version: 2.1
Name: ant-ask-me
Version: 1.2.0
Summary: UNKNOWN
Home-page: https://github.com/qzmlgfj/AskMe
License: UNKNOWN
Platform: UNKNOWN
Requires-Python: >=3.8
Requires-Dist: flask >=2.0.2
Requires-Dist: flask-sqlalchemy >=2.5.1
Requires-Dist: flask-cors >=3.0.10
Requires-Dist: click >=8.0.3
Requires-Dist: gunicorn >=20.1.0
Requires-Dist: pyjwt >=2.5.0
